sitemetrics/__init__.py
sitemetrics/admin.py
sitemetrics/models.py
sitemetrics/providers.py
sitemetrics/settings.py
sitemetrics/utils.py
sitemetrics/locale/ru/LC_MESSAGES/django.mo
sitemetrics/locale/ru/LC_MESSAGES/django.po
sitemetrics/migrations/0001_initial.py
sitemetrics/migrations/__init__.py
sitemetrics/templates/sitemetrics/google.html
sitemetrics/templates/sitemetrics/openstat.html
sitemetrics/templates/sitemetrics/sitemetrics.tpl
sitemetrics/templates/sitemetrics/yandex.html
sitemetrics/templatetags/__init__.py
sitemetrics/templatetags/__init__.pyc
sitemetrics/templatetags/sitemetrics.py
sitemetrics/templatetags/sitemetrics.pyc
sitemetrics/templatetags/__pycache__/__init__.cpython-34.pyc
sitemetrics/templatetags/__pycache__/__init__.cpython-35.pyc
sitemetrics/templatetags/__pycache__/__init__.cpython-36.pyc
sitemetrics/templatetags/__pycache__/sitemetrics.cpython-34.pyc
sitemetrics/templatetags/__pycache__/sitemetrics.cpython-35.pyc
sitemetrics/templatetags/__pycache__/sitemetrics.cpython-36.pyc
sitemetrics/tests/__init__.py
sitemetrics/tests/conftest.py
sitemetrics/tests/test_basic.py
sitemetrics/tests/testapp/__init__.py
sitemetrics/tests/testapp/providers.py
django_sitemetrics-1.2.0.dist-info/AUTHORS
django_sitemetrics-1.2.0.dist-info/LICENSE
django_sitemetrics-1.2.0.dist-info/METADATA
django_sitemetrics-1.2.0.dist-info/WHEEL
django_sitemetrics-1.2.0.dist-info/top_level.txt
django_sitemetrics-1.2.0.dist-info/RECORD
